prefect_sns/__init__.py
prefect_sns/_version.py
prefect_sns/blocks.py
prefect_sns/flows.py
prefect_sns/tasks.py
prefect_sns-0.3.1.dist-info/LICENSE
prefect_sns-0.3.1.dist-info/METADATA
prefect_sns-0.3.1.dist-info/WHEEL
prefect_sns-0.3.1.dist-info/entry_points.txt
prefect_sns-0.3.1.dist-info/top_level.txt
prefect_sns-0.3.1.dist-info/RECORD
